fastprogress/__init__.py
fastprogress/_modidx.py
fastprogress/_nbdev.py
fastprogress/core.py
fastprogress/fastprogress.py
fastprogress/version.py
fastprogress-1.1.3.dist-info/licenses/LICENSE
fastprogress-1.1.3.dist-info/METADATA
fastprogress-1.1.3.dist-info/WHEEL
fastprogress-1.1.3.dist-info/top_level.txt
fastprogress-1.1.3.dist-info/RECORD
