Metadata-Version: 2.4
Name: fastprogress
Version: 1.1.3
Summary: A nested progress with plotting options for fastai
Home-page: https://github.com/answerdotai/fastprogress
Author: Sylvain Gugger and Jeremy Howard
Author-email: info@fast.ai
License: Apache Software License 2.0
Keywords: jupyter notebook progressbar
Classifier: Development Status :: 5 - Production/Stable
Classifier: Intended Audience :: Developers
Classifier: License :: OSI Approved :: Apache Software License
Classifier: Natural Language :: English
Classifier: Programming Language :: Python :: 3.10
Requires-Python: >=3.10
License-File: LICENSE
Requires-Dist: fastcore>=1.10.0
Requires-Dist: python-fasthtml>=0.12.34
Dynamic: author
Dynamic: author-email
Dynamic: classifier
Dynamic: description
Dynamic: description-content-type
Dynamic: home-page
Dynamic: keywords
Dynamic: license
Dynamic: license-file
Dynamic: requires-dist
Dynamic: requires-python
Dynamic: summary
